HelpyFuncs/DataFrames.py
HelpyFuncs/Dicts.py
HelpyFuncs/Geometry2D.py
HelpyFuncs/Print.py
HelpyFuncs/SymPy.py
HelpyFuncs/Visualizations.py
HelpyFuncs/__init__.py
HelpyFuncs/zzz.py
HelpyFuncs-0.0.1.dist-info/DESCRIPTION.rst
HelpyFuncs-0.0.1.dist-info/METADATA
HelpyFuncs-0.0.1.dist-info/RECORD
HelpyFuncs-0.0.1.dist-info/WHEEL
HelpyFuncs-0.0.1.dist-info/metadata.json
HelpyFuncs-0.0.1.dist-info/top_level.txt
